{
  "classname": null,
  "name": null,
  "animation": {
    "classname": null,
    "name": "AnimationManager",
    "actionlist": []
  },
  "dataScale": 1,
  "designHeight": 800,
  "designWidth": 480,
  "textures": [
    "uiAtlas.plist",
    "uiAtlas1.plist"
  ],
  "texturesPng": [
    "uiAtlas.plist",
    "GUI/image.png",
    "uiAtlas.plist",
    "uiAtlas.plist",
    "uiAtlas.plist",
    "uiAtlas.plist",
    "uiAtlas.plist",
    "uiAtlas.plist",
    "vip_bg.jpg",
    "uiAtlas.plist",
    "uiAtlas.plist",
    "uiAtlas.plist",
    "uiAtlas.plist",
    "guanqiaxuanze_beijing.jpg",
    "GUI/image.png",
    "zhujiemian_beijing.jpg",
    "uiAtlas.plist",
    "uiAtlas.plist",
    "guanqiaxuanze_beijing.jpg",
    "uiAtlas.plist",
    "zhanjixuanze_beijing.jpg",
    "uiAtlas.plist"
  ],
  "version": "1.6.0.0",
  "widgetTree": {
    "classname": "Panel",
    "name": null,
    "children": [
      {
        "classname": "Panel",
        "name": null,
        "children": [
          {
            "classname": "ImageView",
            "name": null,
            "children": [],
            "options": {
              "__type": "ImageViewSurrogate:#EditorCommon.JsonModel.Component.GUI",
              "classname": "ImageView",
              "name": "Image_2",
              "ZOrder": 0,
              "actiontag": 60888052,
              "anchorPointX": 0.5,
              "anchorPointY": 0.5,
              "classType": "CocoStudio.EngineAdapterWrap.CSImageView",
              "colorB": 255,
              "colorG": 255,
              "colorR": 255,
              "customProperty": "",
              "flipX": false,
              "flipY": false,
              "height": 306,
              "ignoreSize": true,
              "layoutParameter": null,
              "opacity": 255,
              "positionPercentX": 0,
              "positionPercentY": 0.205454543,
              "positionType": 1,
              "rotation": 0,
              "scaleX": 1,
              "scaleY": 1,
              "sizePercentX": 1.0177778,
              "sizePercentY": 0.556363642,
              "sizeType": 0,
              "tag": 300,
              "touchAble": false,
              "useMergedTexture": false,
              "visible": true,
              "width": 458,
              "x": 0,
              "y": 113,
              "capInsetsHeight": 1,
              "capInsetsWidth": 1,
              "capInsetsX": 0,
              "capInsetsY": 0,
              "fileName": null,
              "fileNameData": {
                "path": "dikuang_choujian02.png",
                "plistFile": "uiAtlas.plist",
                "resourceType": 1
              },
              "scale9Enable": false,
              "scale9Height": 306,
              "scale9Width": 458
            }
          },
          {
            "classname": "ImageView",
            "name": null,
            "children": [],
            "options": {
              "__type": "ImageViewSurrogate:#EditorCommon.JsonModel.Component.GUI",
              "classname": "ImageView",
              "name": "Image_3",
              "ZOrder": 0,
              "actiontag": 25684091,
              "anchorPointX": 0.5,
              "anchorPointY": 0.5,
              "classType": "CocoStudio.EngineAdapterWrap.CSImageView",
              "colorB": 255,
              "colorG": 255,
              "colorR": 255,
              "customProperty": "",
              "flipX": false,
              "flipY": false,
              "height": 18,
              "ignoreSize": true,
              "layoutParameter": null,
              "opacity": 255,
              "positionPercentX": 0,
              "positionPercentY": -0.312727273,
              "positionType": 1,
              "rotation": 0,
              "scaleX": 1,
              "scaleY": 20,
              "sizePercentX": 0.9688889,
              "sizePercentY": 0.03272727,
              "sizeType": 0,
              "tag": 301,
              "touchAble": false,
              "useMergedTexture": false,
              "visible": true,
              "width": 436,
              "x": 0,
              "y": -172,
              "capInsetsHeight": 1,
              "capInsetsWidth": 1,
              "capInsetsX": 0,
              "capInsetsY": 0,
              "fileName": null,
              "fileNameData": {
                "path": "dikuang_choujian03.png",
                "plistFile": "uiAtlas.plist",
                "resourceType": 1
              },
              "scale9Enable": false,
              "scale9Height": 18,
              "scale9Width": 436
            }
          },
          {
            "classname": "ImageView",
            "name": null,
            "children": [],
            "options": {
              "__type": "ImageViewSurrogate:#EditorCommon.JsonModel.Component.GUI",
              "classname": "ImageView",
              "name": "Image_4",
              "ZOrder": 0,
              "actiontag": 12354655,
              "anchorPointX": 0.5,
              "anchorPointY": 0.5,
              "classType": "CocoStudio.EngineAdapterWrap.CSImageView",
              "colorB": 255,
              "colorG": 255,
              "colorR": 255,
              "customProperty": "",
              "flipX": false,
              "flipY": false,
              "height": 64,
              "ignoreSize": true,
              "layoutParameter": null,
              "opacity": 255,
              "positionPercentX": 0,
              "positionPercentY": -0.625454545,
              "positionType": 0,
              "rotation": 0,
              "scaleX": 1,
              "scaleY": 1,
              "sizePercentX": 1.0155555,
              "sizePercentY": 0.116363637,
              "sizeType": 0,
              "tag": 302,
              "touchAble": false,
              "useMergedTexture": false,
              "visible": true,
              "width": 457,
              "x": 0,
              "y": -344,
              "capInsetsHeight": 1,
              "capInsetsWidth": 1,
              "capInsetsX": 0,
              "capInsetsY": 0,
              "fileName": null,
              "fileNameData": {
                "path": "dikuang_choujian04.png",
                "plistFile": "uiAtlas.plist",
                "resourceType": 1
              },
              "scale9Enable": false,
              "scale9Height": 64,
              "scale9Width": 457
            }
          },
          {
            "classname": "ImageView",
            "name": null,
            "children": [
              {
                "classname": "ImageView",
                "name": null,
                "children": [],
                "options": {
                  "__type": "ImageViewSurrogate:#EditorCommon.JsonModel.Component.GUI",
                  "classname": "ImageView",
                  "name": "Image_7",
                  "ZOrder": 0,
                  "actiontag": 55261438,
                  "anchorPointX": 0.5,
                  "anchorPointY": 0.5,
                  "classType": "CocoStudio.EngineAdapterWrap.CSImageView",
                  "colorB": 255,
                  "colorG": 255,
                  "colorR": 255,
                  "customProperty": "",
                  "flipX": false,
                  "flipY": false,
                  "height": 26,
                  "ignoreSize": true,
                  "layoutParameter": null,
                  "opacity": 255,
                  "positionPercentX": 0,
                  "positionPercentY": 0,
                  "positionType": 1,
                  "rotation": 0,
                  "scaleX": 1,
                  "scaleY": 1,
                  "sizePercentX": 0.286069661,
                  "sizePercentY": 0.3561644,
                  "sizeType": 0,
                  "tag": 305,
                  "touchAble": false,
                  "useMergedTexture": false,
                  "visible": true,
                  "width": 115,
                  "x": 0,
                  "y": 0,
                  "capInsetsHeight": 1,
                  "capInsetsWidth": 1,
                  "capInsetsX": 0,
                  "capInsetsY": 0,
                  "fileName": null,
                  "fileNameData": {
                    "path": "paihangbang_biaoti.png",
                    "plistFile": "uiAtlas.plist",
                    "resourceType": 1
                  },
                  "scale9Enable": false,
                  "scale9Height": 26,
                  "scale9Width": 115
                }
              }
            ],
            "options": {
              "__type": "ImageViewSurrogate:#EditorCommon.JsonModel.Component.GUI",
              "classname": "ImageView",
              "name": "Image_6",
              "ZOrder": 0,
              "actiontag": 45319205,
              "anchorPointX": 0.5,
              "anchorPointY": 0.5,
              "classType": "CocoStudio.EngineAdapterWrap.CSImageView",
              "colorB": 255,
              "colorG": 255,
              "colorR": 255,
              "customProperty": "",
              "flipX": false,
              "flipY": false,
              "height": 73,
              "ignoreSize": true,
              "layoutParameter": null,
              "opacity": 255,
              "positionPercentX": -0.008888889,
              "positionPercentY": 0.467272729,
              "positionType": 0,
              "rotation": 0,
              "scaleX": 1,
              "scaleY": 1,
              "sizePercentX": 0.8933333,
              "sizePercentY": 0.132727265,
              "sizeType": 0,
              "tag": 304,
              "touchAble": false,
              "useMergedTexture": false,
              "visible": true,
              "width": 402,
              "x": -4,
              "y": 257,
              "capInsetsHeight": 1,
              "capInsetsWidth": 1,
              "capInsetsX": 0,
              "capInsetsY": 0,
              "fileName": null,
              "fileNameData": {
                "path": "dikuang_hengtiao.png",
                "plistFile": "uiAtlas.plist",
                "resourceType": 1
              },
              "scale9Enable": false,
              "scale9Height": 73,
              "scale9Width": 402
            }
          },
          {
            "classname": "ImageView",
            "name": null,
            "children": [],
            "options": {
              "__type": "ImageViewSurrogate:#EditorCommon.JsonModel.Component.GUI",
              "classname": "ImageView",
              "name": "Image_8",
              "ZOrder": 0,
              "actiontag": 48631485,
              "anchorPointX": 0.5,
              "anchorPointY": 0.5,
              "classType": "CocoStudio.EngineAdapterWrap.CSImageView",
              "colorB": 255,
              "colorG": 255,
              "colorR": 255,
              "customProperty": "",
              "flipX": false,
              "flipY": false,
              "height": 21,
              "ignoreSize": true,
              "layoutParameter": null,
              "opacity": 255,
              "positionPercentX": -0.311111122,
              "positionPercentY": 0.347272724,
              "positionType": 0,
              "rotation": 0,
              "scaleX": 1,
              "scaleY": 1,
              "sizePercentX": 0.111111112,
              "sizePercentY": 0.03818182,
              "sizeType": 0,
              "tag": 306,
              "touchAble": false,
              "useMergedTexture": false,
              "visible": true,
              "width": 50,
              "x": -140,
              "y": 191,
              "capInsetsHeight": 1,
              "capInsetsWidth": 1,
              "capInsetsX": 0,
              "capInsetsY": 0,
              "fileName": null,
              "fileNameData": {
                "path": "paihangbang_fubiaoti.png",
                "plistFile": "uiAtlas.plist",
                "resourceType": 1
              },
              "scale9Enable": false,
              "scale9Height": 21,
              "scale9Width": 50
            }
          },
          {
            "classname": "ImageView",
            "name": null,
            "children": [],
            "options": {
              "__type": "ImageViewSurrogate:#EditorCommon.JsonModel.Component.GUI",
              "classname": "ImageView",
              "name": "Image_9",
              "ZOrder": 0,
              "actiontag": 46728145,
              "anchorPointX": 0.5,
              "anchorPointY": 0.5,
              "classType": "CocoStudio.EngineAdapterWrap.CSImageView",
              "colorB": 255,
              "colorG": 255,
              "colorR": 255,
              "customProperty": "",
              "flipX": false,
              "flipY": false,
              "height": 22,
              "ignoreSize": true,
              "layoutParameter": null,
              "opacity": 255,
              "positionPercentX": 0,
              "positionPercentY": 0.3490909,
              "positionType": 0,
              "rotation": 0,
              "scaleX": 1,
              "scaleY": 1,
              "sizePercentX": 0.111111112,
              "sizePercentY": 0.04,
              "sizeType": 0,
              "tag": 307,
              "touchAble": false,
              "useMergedTexture": false,
              "visible": true,
              "width": 50,
              "x": 0,
              "y": 192,
              "capInsetsHeight": 1,
              "capInsetsWidth": 1,
              "capInsetsX": 0,
              "capInsetsY": 0,
              "fileName": null,
              "fileNameData": {
                "path": "paihangbang_mingcheng.png",
                "plistFile": "uiAtlas.plist",
                "resourceType": 1
              },
              "scale9Enable": false,
              "scale9Height": 22,
              "scale9Width": 50
            }
          },
          {
            "classname": "ImageView",
            "name": null,
            "children": [],
            "options": {
              "__type": "ImageViewSurrogate:#EditorCommon.JsonModel.Component.GUI",
              "classname": "ImageView",
              "name": "Image_10",
              "ZOrder": 0,
              "actiontag": 3604747,
              "anchorPointX": 0.5,
              "anchorPointY": 0.5,
              "classType": "CocoStudio.EngineAdapterWrap.CSImageView",
              "colorB": 255,
              "colorG": 255,
              "colorR": 255,
              "customProperty": "",
              "flipX": false,
              "flipY": false,
              "height": 22,
              "ignoreSize": true,
              "layoutParameter": null,
              "opacity": 255,
              "positionPercentX": 0.304444432,
              "positionPercentY": 0.352727264,
              "positionType": 0,
              "rotation": 0,
              "scaleX": 1,
              "scaleY": 1,
              "sizePercentX": 0.113333337,
              "sizePercentY": 0.04,
              "sizeType": 0,
              "tag": 308,
              "touchAble": false,
              "useMergedTexture": false,
              "visible": true,
              "width": 51,
              "x": 137,
              "y": 194,
              "capInsetsHeight": 1,
              "capInsetsWidth": 1,
              "capInsetsX": 0,
              "capInsetsY": 0,
              "fileName": null,
              "fileNameData": {
                "path": "paihangbang_fenshu.png",
                "plistFile": "uiAtlas.plist",
                "resourceType": 1
              },
              "scale9Enable": false,
              "scale9Height": 22,
              "scale9Width": 51
            }
          },
          {
            "classname": "ScrollView",
            "name": null,
            "children": [],
            "options": {
              "__type": "ScrollViewSurrogate:#EditorCommon.JsonModel.Component.GUI",
              "classname": "ScrollView",
              "name": "ScrollView_11",
              "ZOrder": 0,
              "actiontag": 1059799,
              "anchorPointX": 0,
              "anchorPointY": 0,
              "classType": "CocoStudio.EngineAdapterWrap.CSScrollView",
              "colorB": 255,
              "colorG": 255,
              "colorR": 255,
              "customProperty": "",
              "flipX": false,
              "flipY": false,
              "height": 510,
              "ignoreSize": false,
              "layoutParameter": null,
              "opacity": 255,
              "positionPercentX": -0.422222227,
              "positionPercentY": -0.6381818,
              "positionType": 1,
              "rotation": 0,
              "scaleX": 1,
              "scaleY": 1,
              "sizePercentX": 0.844444454,
              "sizePercentY": 0.927272737,
              "sizeType": 0,
              "tag": 309,
              "touchAble": true,
              "useMergedTexture": false,
              "visible": true,
              "width": 380,
              "x": -190,
              "y": -351,
              "backGroundImage": null,
              "backGroundImageData": null,
              "backGroundScale9Enable": false,
              "bgColorB": 100,
              "bgColorG": 150,
              "bgColorOpacity": 56,
              "bgColorR": 255,
              "bgEndColorB": 100,
              "bgEndColorG": 150,
              "bgEndColorR": 255,
              "bgStartColorB": 255,
              "bgStartColorG": 255,
              "bgStartColorR": 255,
              "bounceEnable": true,
              "capInsetsHeight": 1,
              "capInsetsWidth": 1,
              "capInsetsX": 0,
              "capInsetsY": 0,
              "clipAble": false,
              "colorType": 1,
              "direction": 1,
              "editorClipAble": false,
              "innerHeight": 510,
              "innerWidth": 380,
              "layoutType": 0,
              "vectorX": 0,
              "vectorY": -0.5
            }
          }
        ],
        "options": {
          "__type": "PanelSurrogate:#EditorCommon.JsonModel.Component.GUI",
          "classname": "Panel",
          "name": "Panel_board",
          "ZOrder": 0,
          "actiontag": 21896289,
          "anchorPointX": 0,
          "anchorPointY": 0,
          "classType": "CocoStudio.EngineAdapterWrap.CSPanel",
          "colorB": 255,
          "colorG": 255,
          "colorR": 255,
          "customProperty": "",
          "flipX": false,
          "flipY": false,
          "height": 550,
          "ignoreSize": false,
          "layoutParameter": null,
          "opacity": 255,
          "positionPercentX": 0.5,
          "positionPercentY": 0.595,
          "positionType": 1,
          "rotation": 0,
          "scaleX": 1,
          "scaleY": 1,
          "sizePercentX": 0.9375,
          "sizePercentY": 0.6875,
          "sizeType": 0,
          "tag": 299,
          "touchAble": true,
          "useMergedTexture": false,
          "visible": true,
          "width": 450,
          "x": 240,
          "y": 476,
          "adaptScreen": false,
          "backGroundImage": null,
          "backGroundImageData": null,
          "backGroundScale9Enable": false,
          "bgColorB": 255,
          "bgColorG": 200,
          "bgColorOpacity": 0,
          "bgColorR": 150,
          "bgEndColorB": 255,
          "bgEndColorG": 200,
          "bgEndColorR": 150,
          "bgStartColorB": 255,
          "bgStartColorG": 255,
          "bgStartColorR": 255,
          "capInsetsHeight": 1,
          "capInsetsWidth": 1,
          "capInsetsX": 0,
          "capInsetsY": 0,
          "clipAble": false,
          "colorType": 1,
          "layoutType": 0,
          "vectorX": 0,
          "vectorY": -0.5
        }
      },
      {
        "classname": "Button",
        "name": null,
        "children": [
          {
            "classname": "ImageView",
            "name": null,
            "children": [],
            "options": {
              "__type": "ImageViewSurrogate:#EditorCommon.JsonModel.Component.GUI",
              "classname": "ImageView",
              "name": "Image_1",
              "ZOrder": 0,
              "actiontag": 51418784,
              "anchorPointX": 0.5,
              "anchorPointY": 0.5,
              "classType": "CocoStudio.EngineAdapterWrap.CSImageView",
              "colorB": 255,
              "colorG": 255,
              "colorR": 255,
              "customProperty": "",
              "flipX": false,
              "flipY": false,
              "height": 31,
              "ignoreSize": true,
              "layoutParameter": null,
              "opacity": 255,
              "positionPercentX": 0,
              "positionPercentY": 0,
              "positionType": 0,
              "rotation": 0,
              "scaleX": 1,
              "scaleY": 1,
              "sizePercentX": 0.5,
              "sizePercentY": 0.476923078,
              "sizeType": 0,
              "tag": 1190,
              "touchAble": false,
              "useMergedTexture": false,
              "visible": true,
              "width": 73,
              "x": 0,
              "y": 0,
              "capInsetsHeight": 1,
              "capInsetsWidth": 1,
              "capInsetsX": 0,
              "capInsetsY": 0,
              "fileName": null,
              "fileNameData": {
                "path": "anniu_fanhui02.png",
                "plistFile": "uiAtlas.plist",
                "resourceType": 1
              },
              "scale9Enable": false,
              "scale9Height": 31,
              "scale9Width": 73
            }
          }
        ],
        "options": {
          "__type": "ButtonSurrogate:#EditorCommon.JsonModel.Component.GUI",
          "classname": "Button",
          "name": "Button_back",
          "ZOrder": 0,
          "actiontag": 16538319,
          "anchorPointX": 0.5,
          "anchorPointY": 0.5,
          "classType": "CocoStudio.EngineAdapterWrap.CSButton",
          "colorB": 255,
          "colorG": 255,
          "colorR": 255,
          "customProperty": "",
          "flipX": false,
          "flipY": false,
          "height": 65,
          "ignoreSize": true,
          "layoutParameter": null,
          "opacity": 255,
          "positionPercentX": 0.5,
          "positionPercentY": 0.065,
          "positionType": 1,
          "rotation": 0,
          "scaleX": 1,
          "scaleY": 1,
          "sizePercentX": 0.304166675,
          "sizePercentY": 0.08125,
          "sizeType": 0,
          "tag": 303,
          "touchAble": true,
          "useMergedTexture": false,
          "visible": true,
          "width": 146,
          "x": 240,
          "y": 52,
          "capInsetsHeight": 1,
          "capInsetsWidth": 1,
          "capInsetsX": 0,
          "capInsetsY": 0,
          "disabled": null,
          "disabledData": {
            "path": null,
            "plistFile": null,
            "resourceType": 0
          },
          "fontName": "微软雅黑",
          "fontSize": 14,
          "fontType": 0,
          "normal": null,
          "normalData": {
            "path": "button02.png",
            "plistFile": "uiAtlas.plist",
            "resourceType": 1
          },
          "pressed": null,
          "pressedData": {
            "path": null,
            "plistFile": null,
            "resourceType": 0
          },
          "scale9Enable": false,
          "scale9Height": 65,
          "scale9Width": 146,
          "text": "",
          "textColorB": 255,
          "textColorG": 255,
          "textColorR": 255
        }
      }
    ],
    "options": {
      "__type": "PanelSurrogate:#EditorCommon.JsonModel.Component.GUI",
      "classname": "Panel",
      "name": "Panel_main",
      "ZOrder": 0,
      "actiontag": -1,
      "anchorPointX": 0,
      "anchorPointY": 0,
      "classType": "CocoStudio.EngineAdapterWrap.CSPanel",
      "colorB": 255,
      "colorG": 255,
      "colorR": 255,
      "customProperty": "",
      "flipX": false,
      "flipY": false,
      "height": 800,
      "ignoreSize": false,
      "layoutParameter": null,
      "opacity": 255,
      "positionPercentX": 0,
      "positionPercentY": 0,
      "positionType": 0,
      "rotation": 0,
      "scaleX": 1,
      "scaleY": 1,
      "sizePercentX": 1,
      "sizePercentY": 1,
      "sizeType": 0,
      "tag": 298,
      "touchAble": true,
      "useMergedTexture": false,
      "visible": true,
      "width": 480,
      "x": 0,
      "y": 0,
      "adaptScreen": false,
      "backGroundImage": null,
      "backGroundImageData": null,
      "backGroundScale9Enable": false,
      "bgColorB": 255,
      "bgColorG": 200,
      "bgColorOpacity": 0,
      "bgColorR": 150,
      "bgEndColorB": 255,
      "bgEndColorG": 200,
      "bgEndColorR": 150,
      "bgStartColorB": 255,
      "bgStartColorG": 255,
      "bgStartColorR": 255,
      "capInsetsHeight": 1,
      "capInsetsWidth": 1,
      "capInsetsX": 0,
      "capInsetsY": 0,
      "clipAble": false,
      "colorType": 1,
      "layoutType": 0,
      "vectorX": 0,
      "vectorY": -0.5
    }
  }
}